karbonn/__init__.py
karbonn/distributed/__init__.py
karbonn/distributed/ddp.py
karbonn/distributed/utils.py
karbonn/functional/__init__.py
karbonn/functional/activations/__init__.py
karbonn/functional/activations/math.py
karbonn/functional/error.py
karbonn/functional/loss/__init__.py
karbonn/functional/loss/asinh.py
karbonn/functional/loss/general_robust.py
karbonn/functional/loss/log.py
karbonn/functional/loss/relative.py
karbonn/functional/reduction.py
karbonn/metric/__init__.py
karbonn/metric/base.py
karbonn/metric/classification/__init__.py
karbonn/metric/classification/accuracy.py
karbonn/metric/classification/confmat.py
karbonn/metric/classification/entropy.py
karbonn/metric/regression/__init__.py
karbonn/metric/regression/absolute_error.py
karbonn/metric/regression/absolute_relative_error.py
karbonn/metric/regression/log_cosh_error.py
karbonn/metric/regression/nmse.py
karbonn/metric/regression/squared_error.py
karbonn/metric/regression/squared_log_error.py
karbonn/metric/state/__init__.py
karbonn/metric/state/accuracy.py
karbonn/metric/state/base.py
karbonn/metric/state/error.py
karbonn/metric/state_.py
karbonn/modules/__init__.py
karbonn/modules/activations/__init__.py
karbonn/modules/activations/alpha.py
karbonn/modules/activations/math.py
karbonn/modules/activations/relu.py
karbonn/modules/activations/snake.py
karbonn/modules/clamp.py
karbonn/modules/classification.py
karbonn/modules/dtype.py
karbonn/modules/exu.py
karbonn/modules/fusion/__init__.py
karbonn/modules/fusion/aggregation.py
karbonn/modules/fusion/concat.py
karbonn/modules/loss/__init__.py
karbonn/modules/loss/asinh.py
karbonn/modules/loss/focal.py
karbonn/modules/loss/general_robust.py
karbonn/modules/loss/indicators.py
karbonn/modules/loss/relative.py
karbonn/modules/loss/transform.py
karbonn/modules/nlinear.py
karbonn/modules/numerical/__init__.py
karbonn/modules/numerical/asinh.py
karbonn/modules/numerical/piecewise.py
karbonn/modules/numerical/sine.py
karbonn/modules/residual.py
karbonn-0.0.3.dist-info/LICENSE
karbonn-0.0.3.dist-info/METADATA
karbonn-0.0.3.dist-info/WHEEL
karbonn-0.0.3.dist-info/RECORD
